odoo/addons/so_sequence_duplicate_confirmed_order_type/README.rst
odoo/addons/so_sequence_duplicate_confirmed_order_type/__init__.py
odoo/addons/so_sequence_duplicate_confirmed_order_type/__manifest__.py
odoo/addons/so_sequence_duplicate_confirmed_order_type/models/__init__.py
odoo/addons/so_sequence_duplicate_confirmed_order_type/models/sale_order.py
odoo/addons/so_sequence_duplicate_confirmed_order_type/static/description/icon.png
odoo_addon_so_sequence_duplicate_confirmed_order_type-15.0.1.0.0.3.dist-info/METADATA
odoo_addon_so_sequence_duplicate_confirmed_order_type-15.0.1.0.0.3.dist-info/WHEEL
odoo_addon_so_sequence_duplicate_confirmed_order_type-15.0.1.0.0.3.dist-info/top_level.txt
odoo_addon_so_sequence_duplicate_confirmed_order_type-15.0.1.0.0.3.dist-info/RECORD
